{"is_source_file": true, "format": "Python", "description": "This is an __init__.py file for the Jira connector package, likely used for package initialization and documentation purposes.", "external_files": [], "external_methods": [], "published": [], "classes": [], "methods": [], "calls": [], "search-terms": ["jira", "connector", "package", "__init__", "unified_connector_backend"], "state": 2, "file_id": 36, "knowledge_revision": 89, "git_revision": "", "ctags": [], "hash": "1b716172c722e2e142b98bd4425663f2", "format-version": 4, "code-base-name": "unified_connector_backend", "filename": "unified_connector_backend/src/connectors/jira/__init__.py", "revision_history": [{"89": ""}]}